README.rst
setup.py
confirm/__init__.py
confirm/generator.py
confirm/main.py
confirm/utils.py
confirm/validator.py
confirm.egg-info/PKG-INFO
confirm.egg-info/SOURCES.txt
confirm.egg-info/dependency_links.txt
confirm.egg-info/entry_points.txt
confirm.egg-info/requires.txt
confirm.egg-info/top_level.txt