Metadata-Version: 1.1
Name: confirm
Version: 0.1.2
Summary: Simple Python configuration file management.
Home-page: https://github.com/louib/confirm
Author: Louis-Bertrand Varin
Author-email: louisbvarin@gmail.com
License: MIT
Platform: UNKNOWN
Classifier: Programming Language :: Python
Classifier: Development Status :: 3 - Alpha
Classifier: Intended Audience :: Developers
Classifier: Intended Audience :: System Administrators
Classifier: Topic :: Utilities
Classifier: License :: OSI Approved :: MIT License
